[{"ts": "2026-02-21T07:58:30.067871+01:00", "temp": 4.0, "pressione": 1034.7, "pioggia_1h": 0.0, "pioggia_24h": 0.0, "umidita": 87, "vento": 11.1, "raffica": 11.1, "dew_point": 2.0, "api": 173.12, "sbcape": 0, "mucape": 0, "bulk_shear": 2.6, "theta_e": 13.0}, {"ts": "2026-02-21T08:06:55.650277+01:00", "temp": 4.0, "pressione": 1035.7, "pioggia_1h": 0.0, "pioggia_24h": 0.0, "umidita": 93, "vento": 11.1, "raffica": 11.1, "dew_point": 3.0, "api": 173.12, "sbcape": 0, "mucape": 0, "bulk_shear": 2.2, "theta_e": 13.8}, {"ts": "2026-02-21T08:58:35.605359+01:00", "temp": 4.0, "pressione": 1035.7, "pioggia_1h": 0.0, "pioggia_24h": 0.0, "umidita": 93, "vento": 11.1, "raffica": 11.1, "dew_point": 3.0, "api": 173.1, "sbcape": 0, "mucape": 0, "bulk_shear": 2.2, "theta_e": 13.8}, {"ts": "2026-02-21T09:58:30.483489+01:00", "temp": 8.0, "pressione": 1036.5, "pioggia_1h": 0.0, "pioggia_24h": 0.0, "umidita": 76, "vento": 5.6, "raffica": 5.6, "dew_point": 4.0, "api": 173.02, "sbcape": 0, "mucape": 0, "bulk_shear": 1.2, "theta_e": 18.8}, {"ts": "2026-02-21T10:00:41.306398+01:00", "temp": 8.0, "pressione": 1036.5, "pioggia_1h": 0.0, "pioggia_24h": 0.0, "umidita": 76, "vento": 5.6, "raffica": 5.6, "dew_point": 4.0, "api": 173.02, "sbcape": 0, "mucape": 0, "bulk_shear": 0.1, "theta_e": 18.8}, {"ts": "2026-02-21T10:58:29.064380+01:00", "temp": 11.0, "pressione": 1036.4, "pioggia_1h": 0.0, "pioggia_24h": 0.0, "umidita": 71, "vento": 3.7, "raffica": 3.7, "dew_point": 6.0, "api": 172.85, "sbcape": 0, "mucape": 0, "bulk_shear": 0.7, "theta_e": 23.9}, {"ts": "2026-02-21T11:55:45.244202+01:00", "temp": 13.0, "pressione": 1036.3, "pioggia_1h": 0.0, "pioggia_24h": 0.0, "umidita": 67, "vento": 5.6, "raffica": 5.6, "dew_point": 7.0, "api": 172.72, "sbcape": 0, "mucape": 0, "bulk_shear": 0.4, "theta_e": 27.1}, {"ts": "2026-02-21T11:58:30.320634+01:00", "temp": 13.0, "pressione": 1036.3, "pioggia_1h": 0.0, "pioggia_24h": 0.0, "umidita": 67, "vento": 5.6, "raffica": 5.6, "dew_point": 7.0, "api": 172.72, "sbcape": 0, "mucape": 0, "bulk_shear": 0.4, "theta_e": 27.1}, {"ts": "2026-02-21T12:41:40.121418+01:00", "temp": 13.0, "pressione": 1036.3, "pioggia_1h": 0.0, "pioggia_24h": 0.0, "umidita": 67, "vento": 9.3, "raffica": 9.3, "dew_point": 7.0, "api": 172.68, "sbcape": 0, "mucape": 0, "bulk_shear": 2.3, "theta_e": 27.1}, {"ts": "2026-02-21T12:58:30.048488+01:00", "temp": 13.0, "pressione": 1036.3, "pioggia_1h": 0.0, "pioggia_24h": 0.0, "umidita": 67, "vento": 9.3, "raffica": 9.3, "dew_point": 7.0, "api": 172.67, "sbcape": 0, "mucape": 0, "bulk_shear": 2.3, "theta_e": 27.1}, {"ts": "2026-02-21T13:58:27.424497+01:00", "temp": 15.0, "pressione": 1035.2, "pioggia_1h": 0.0, "pioggia_24h": 0.0, "umidita": 59, "vento": 11.1, "raffica": 11.1, "dew_point": 7.0, "api": 172.51, "sbcape": 0, "mucape": 0, "bulk_shear": 1.7, "theta_e": 29.4}, {"ts": "2026-02-21T14:54:37.800930+01:00", "temp": 14.0, "pressione": 1035.2, "pioggia_1h": 0.0, "pioggia_24h": 0.0, "umidita": 63, "vento": 13.0, "raffica": 13.0, "dew_point": 7.0, "api": 172.45, "sbcape": 0, "mucape": 0, "bulk_shear": 0.8, "theta_e": 28.3}, {"ts": "2026-02-21T14:58:29.249483+01:00", "temp": 14.0, "pressione": 1035.2, "pioggia_1h": 0.0, "pioggia_24h": 0.0, "umidita": 63, "vento": 13.0, "raffica": 13.0, "dew_point": 7.0, "api": 172.45, "sbcape": 0, "mucape": 0, "bulk_shear": 0.8, "theta_e": 28.3}, {"ts": "2026-02-21T15:55:05.732773+01:00", "temp": 14.0, "pressione": 1035.2, "pioggia_1h": 0.0, "pioggia_24h": 0.0, "umidita": 63, "vento": 9.3, "raffica": 9.3, "dew_point": 7.0, "api": 172.39, "sbcape": 0, "mucape": 0, "bulk_shear": 0.5, "theta_e": 28.3}, {"ts": "2026-02-21T16:49:27.444379+01:00", "temp": 14.0, "pressione": 1034.2, "pioggia_1h": 0.0, "pioggia_24h": 0.0, "umidita": 63, "vento": 7.4, "raffica": 7.4, "dew_point": 7.0, "api": 172.34, "sbcape": 0, "mucape": 0, "bulk_shear": 0.5, "theta_e": 28.4}, {"ts": "2026-02-21T16:58:29.333777+01:00", "temp": 14.0, "pressione": 1034.2, "pioggia_1h": 0.0, "pioggia_24h": 0.0, "umidita": 63, "vento": 7.4, "raffica": 7.4, "dew_point": 7.0, "api": 172.33, "sbcape": 0, "mucape": 0, "bulk_shear": 0.5, "theta_e": 28.4}, {"ts": "2026-02-21T17:58:38.411169+01:00", "temp": 14.0, "pressione": 1035.2, "pioggia_1h": 0.0, "pioggia_24h": 0.0, "umidita": 63, "vento": 5.6, "raffica": 5.6, "dew_point": 7.0, "api": 172.27, "sbcape": 0, "mucape": 0, "bulk_shear": 0.2, "theta_e": 28.3}, {"ts": "2026-02-21T17:59:42.881970+01:00", "temp": 14.0, "pressione": 1035.2, "pioggia_1h": 0.0, "pioggia_24h": 0.0, "umidita": 63, "vento": 5.6, "raffica": 5.6, "dew_point": 7.0, "api": 172.27, "sbcape": 0, "mucape": 0, "bulk_shear": 0.2, "theta_e": 28.3}, {"ts": "2026-02-21T18:53:27.811363+01:00", "temp": 12.0, "pressione": 1035.3, "pioggia_1h": 0.0, "pioggia_24h": 0.0, "umidita": 77, "vento": 5.6, "raffica": 5.6, "dew_point": 8.0, "api": 172.21, "sbcape": 0, "mucape": 0, "bulk_shear": 0.8, "theta_e": 27.3}, {"ts": "2026-02-21T18:58:28.856411+01:00", "temp": 12.0, "pressione": 1035.3, "pioggia_1h": 0.0, "pioggia_24h": 0.0, "umidita": 77, "vento": 5.6, "raffica": 5.6, "dew_point": 8.0, "api": 172.21, "sbcape": 0, "mucape": 0, "bulk_shear": 0.8, "theta_e": 27.3}, {"ts": "2026-02-21T19:58:45.478474+01:00", "temp": 11.0, "pressione": 1036.4, "pioggia_1h": 0.0, "pioggia_24h": 0.0, "umidita": 76, "vento": 1.9, "raffica": 1.9, "dew_point": 7.0, "api": 172.15, "sbcape": 0, "mucape": 0, "bulk_shear": 0.7, "theta_e": 25.0}, {"ts": "2026-02-21T20:04:32.235653+01:00", "temp": 11.0, "pressione": 1036.4, "pioggia_1h": 0.0, "pioggia_24h": 0.0, "umidita": 76, "vento": 1.9, "raffica": 1.9, "dew_point": 7.0, "api": 172.14, "sbcape": 0, "mucape": 0, "bulk_shear": 0.1, "theta_e": 25.0}, {"ts": "2026-02-21T20:58:31.813827+01:00", "temp": 9.0, "pressione": 1036.5, "pioggia_1h": 0.0, "pioggia_24h": 0.0, "umidita": 81, "vento": 1.9, "raffica": 1.9, "dew_point": 6.0, "api": 172.09, "sbcape": 0, "mucape": 0, "bulk_shear": 0.1, "theta_e": 21.8}, {"ts": "2026-02-21T21:50:19.020080+01:00", "temp": 8.0, "pressione": 1036.5, "pioggia_1h": 0.0, "pioggia_24h": 0.0, "umidita": 93, "vento": 5.6, "raffica": 5.6, "dew_point": 7.0, "api": 172.04, "sbcape": 0, "mucape": 0, "bulk_shear": 0.5, "theta_e": 21.8}, {"ts": "2026-02-21T21:58:31.140146+01:00", "temp": 8.0, "pressione": 1036.5, "pioggia_1h": 0.0, "pioggia_24h": 0.0, "umidita": 93, "vento": 5.6, "raffica": 5.6, "dew_point": 7.0, "api": 172.03, "sbcape": 0, "mucape": 0, "bulk_shear": 0.5, "theta_e": 21.8}, {"ts": "2026-02-21T22:43:53.788416+01:00", "temp": 8.0, "pressione": 1037.5, "pioggia_1h": 0.0, "pioggia_24h": 0.0, "umidita": 87, "vento": 5.6, "raffica": 5.6, "dew_point": 6.0, "api": 171.99, "sbcape": 0, "mucape": 0, "bulk_shear": 0.4, "theta_e": 20.6}, {"ts": "2026-02-21T22:51:53.774501+01:00", "temp": 8.0, "pressione": 1037.5, "pioggia_1h": 0.0, "pioggia_24h": 0.0, "umidita": 87, "vento": 0.0, "raffica": 0, "dew_point": 6.0, "api": 171.98, "sbcape": 0, "mucape": 0, "bulk_shear": 1.1, "theta_e": 20.6}, {"ts": "2026-02-21T22:58:32.150879+01:00", "temp": 8.0, "pressione": 1037.5, "pioggia_1h": 0.0, "pioggia_24h": 0.0, "umidita": 87, "vento": 0.0, "raffica": 0, "dew_point": 6.0, "api": 171.97, "sbcape": 0, "mucape": 0, "bulk_shear": 1.1, "theta_e": 20.6}, {"ts": "2026-02-21T23:58:30.642968+01:00", "temp": 8.0, "pressione": 1037.5, "pioggia_1h": 0.0, "pioggia_24h": 0.0, "umidita": 87, "vento": 0.0, "raffica": 0, "dew_point": 6.0, "api": 171.91, "sbcape": 0, "mucape": 0, "bulk_shear": 1.1, "theta_e": 20.6}, {"ts": "2026-02-22T00:58:34.536748+01:00", "temp": 7.0, "pressione": 1037.6, "pioggia_1h": 0.0, "pioggia_24h": 0.0, "umidita": 93, "vento": 0.0, "raffica": 0, "dew_point": 6.0, "api": 169.37, "sbcape": 0, "mucape": 0, "bulk_shear": 0.3, "theta_e": 19.5}, {"ts": "2026-02-22T01:58:27.612254+01:00", "temp": 7.0, "pressione": 1037.6, "pioggia_1h": 0.0, "pioggia_24h": 0.0, "umidita": 87, "vento": 0.0, "raffica": 0, "dew_point": 5.0, "api": 169.36, "sbcape": 0, "mucape": 0, "bulk_shear": 1.5, "theta_e": 18.6}, {"ts": "2026-02-22T02:58:32.989097+01:00", "temp": 7.0, "pressione": 1037.6, "pioggia_1h": 0.0, "pioggia_24h": 0.0, "umidita": 87, "vento": 0.0, "raffica": 0, "dew_point": 5.0, "api": 169.34, "sbcape": 0, "mucape": 0, "bulk_shear": 1.4, "theta_e": 18.6}, {"ts": "2026-02-22T03:58:31.428830+01:00", "temp": 6.0, "pressione": 1037.6, "pioggia_1h": 0.0, "pioggia_24h": 0.0, "umidita": 93, "vento": 0.0, "raffica": 0, "dew_point": 5.0, "api": 169.32, "sbcape": 0, "mucape": 0, "bulk_shear": 0.5, "theta_e": 17.5}, {"ts": "2026-02-22T04:58:31.404569+01:00", "temp": 5.0, "pressione": 1037.7, "pioggia_1h": 0.0, "pioggia_24h": 0.0, "umidita": 93, "vento": 0.0, "raffica": 0, "dew_point": 4.0, "api": 169.28, "sbcape": 0, "mucape": 0, "bulk_shear": 0.6, "theta_e": 15.5}, {"ts": "2026-02-22T05:58:32.476226+01:00", "temp": 5.0, "pressione": 1037.7, "pioggia_1h": 0.0, "pioggia_24h": 0.0, "umidita": 93, "vento": 0.0, "raffica": 0, "dew_point": 4.0, "api": 169.26, "sbcape": 0, "mucape": 0, "bulk_shear": 1.0, "theta_e": 15.5}, {"ts": "2026-02-22T06:58:29.152926+01:00", "temp": 5.0, "pressione": 1037.7, "pioggia_1h": 0.0, "pioggia_24h": 0.0, "umidita": 93, "vento": 0.0, "raffica": 0, "dew_point": 4.0, "api": 169.23, "sbcape": 0, "mucape": 0, "bulk_shear": 0.4, "theta_e": 15.5}, {"ts": "2026-02-22T07:58:27.911009+01:00", "temp": 5.0, "pressione": 1038.7, "pioggia_1h": 0.0, "pioggia_24h": 0.0, "umidita": 93, "vento": 0.0, "raffica": 0, "dew_point": 4.0, "api": 169.21, "sbcape": 0, "mucape": 0, "bulk_shear": 0.7, "theta_e": 15.4}]